{
  "test_date": "2026-03-02T00:04:20.760696",
  "source": "metbugat.gov.tm (ID 3929..3905)",
  "source_type": "metbugat",
  "articles": 13,
  "results": {
    "total_tokens": 10179,
    "total_types": 3105,
    "recognized_tokens": 7970,
    "unrecognized_tokens": 2209,
    "recognized_types": 2154,
    "unrecognized_types": 951,
    "token_coverage_pct": 78.3,
    "type_coverage_pct": 69.37,
    "top_unrecognized": [
      [
        "hem-de",
        48
      ],
      [
        "golf",
        35
      ],
      [
        "alnyp",
        32
      ],
      [
        "nji",
        27
      ],
      [
        "mundan",
        25
      ],
      [
        "beýläk-de",
        21
      ],
      [
        "çäklerinde",
        19
      ],
      [
        "berdimuhamedow",
        17
      ],
      [
        "has-da",
        15
      ],
      [
        "şunda",
        15
      ],
      [
        "ösdürmek",
        15
      ],
      [
        "ösdürmegiň",
        14
      ],
      [
        "birnäçe",
        14
      ],
      [
        "abş-nyň",
        14
      ],
      [
        "üstünlikli",
        13
      ],
      [
        "şeýle-de",
        12
      ],
      [
        "ösüş",
        12
      ],
      [
        "munuň",
        12
      ],
      [
        "öňünde",
        11
      ],
      [
        "ýokarlandyrmak",
        11
      ],
      [
        "gönükdirilen",
        11
      ],
      [
        "şäherinde",
        11
      ],
      [
        "diýlip",
        10
      ],
      [
        "artdyrmak",
        10
      ],
      [
        "innowasion",
        10
      ],
      [
        "edýän",
        10
      ],
      [
        "arasyndaky",
        10
      ],
      [
        "ahalteke",
        10
      ],
      [
        "at-myradyň",
        9
      ],
      [
        "ösdürilmegine",
        9
      ],
      [
        "ulanmaga",
        9
      ],
      [
        "goýmak",
        9
      ],
      [
        "nicklaus",
        9
      ],
      [
        "companies",
        9
      ],
      [
        "jon",
        9
      ],
      [
        "riz",
        9
      ],
      [
        "aýdyp",
        9
      ],
      [
        "döretmek",
        8
      ],
      [
        "döwrebaplaşdyrmak",
        8
      ],
      [
        "john",
        8
      ],
      [
        "deere",
        8
      ],
      [
        "gerimli",
        7
      ],
      [
        "durmuş-ykdysady",
        7
      ],
      [
        "ýaşaýyş-durmuş",
        7
      ],
      [
        "toplumlaýyn",
        7
      ],
      [
        "yglan",
        7
      ],
      [
        "bermek",
        7
      ],
      [
        "biridir",
        7
      ],
      [
        "özünde",
        7
      ],
      [
        "öndürmek",
        7
      ],
      [
        "taýýarlamak",
        7
      ],
      [
        "ugry",
        7
      ],
      [
        "geçirmek",
        7
      ],
      [
        "bmg-niň",
        7
      ],
      [
        "döwletiniň",
        7
      ],
      [
        "abş",
        7
      ],
      [
        "işewürlik",
        7
      ],
      [
        "kabinetiniň",
        6
      ],
      [
        "bellenildi",
        6
      ],
      [
        "gowulandyrmak",
        6
      ],
      [
        "giňeltmek",
        6
      ],
      [
        "bolşy",
        6
      ],
      [
        "bellemek",
        6
      ],
      [
        "pugtalandyrmaga",
        6
      ],
      [
        "bellenilen",
        6
      ],
      [
        "oňyn",
        6
      ],
      [
        "hususan-da",
        6
      ],
      [
        "gatnaşmagynda",
        6
      ],
      [
        "hyzmatdaşlyga",
        6
      ],
      [
        "geňeşiniň",
        6
      ],
      [
        "al-arabiýa",
        6
      ],
      [
        "teleýaýlymynyň",
        6
      ],
      [
        "rizwan",
        6
      ],
      [
        "florida",
        6
      ],
      [
        "ynanyşmak",
        6
      ],
      [
        "düzümleriniň",
        6
      ],
      [
        "mejlisinde",
        5
      ],
      [
        "galkynyşy",
        5
      ],
      [
        "eden",
        5
      ],
      [
        "paýtagtymyzda",
        5
      ],
      [
        "pugtalandyrmak",
        5
      ],
      [
        "goýlan",
        5
      ],
      [
        "kämilleşdirmek",
        5
      ],
      [
        "ornaşdyrmak",
        5
      ],
      [
        "saklamak",
        5
      ],
      [
        "köpugurly",
        5
      ],
      [
        "döredildi",
        5
      ],
      [
        "döwletleriniň",
        5
      ],
      [
        "önümleriniň",
        5
      ],
      [
        "giňeltmäge",
        5
      ],
      [
        "gurmak",
        5
      ],
      [
        "edilmegi",
        5
      ],
      [
        "ýazylmak",
        5
      ],
      [
        "halkbank",
        5
      ],
      [
        "and",
        5
      ],
      [
        "other",
        5
      ],
      [
        "services",
        5
      ],
      [
        "ýöriteleşdirilen",
        5
      ],
      [
        "serişdeleriniň",
        5
      ],
      [
        "bedewleriniň",
        5
      ]
    ],
    "recognized_word_types": {
      "noun": 1853,
      "verb": 301
    }
  },
  "top_unrecognized_100": [
    [
      "hem-de",
      48
    ],
    [
      "golf",
      35
    ],
    [
      "alnyp",
      32
    ],
    [
      "nji",
      27
    ],
    [
      "mundan",
      25
    ],
    [
      "beýläk-de",
      21
    ],
    [
      "çäklerinde",
      19
    ],
    [
      "berdimuhamedow",
      17
    ],
    [
      "has-da",
      15
    ],
    [
      "şunda",
      15
    ],
    [
      "ösdürmek",
      15
    ],
    [
      "ösdürmegiň",
      14
    ],
    [
      "birnäçe",
      14
    ],
    [
      "abş-nyň",
      14
    ],
    [
      "üstünlikli",
      13
    ],
    [
      "şeýle-de",
      12
    ],
    [
      "ösüş",
      12
    ],
    [
      "munuň",
      12
    ],
    [
      "öňünde",
      11
    ],
    [
      "ýokarlandyrmak",
      11
    ],
    [
      "gönükdirilen",
      11
    ],
    [
      "şäherinde",
      11
    ],
    [
      "diýlip",
      10
    ],
    [
      "artdyrmak",
      10
    ],
    [
      "innowasion",
      10
    ],
    [
      "edýän",
      10
    ],
    [
      "arasyndaky",
      10
    ],
    [
      "ahalteke",
      10
    ],
    [
      "at-myradyň",
      9
    ],
    [
      "ösdürilmegine",
      9
    ],
    [
      "ulanmaga",
      9
    ],
    [
      "goýmak",
      9
    ],
    [
      "nicklaus",
      9
    ],
    [
      "companies",
      9
    ],
    [
      "jon",
      9
    ],
    [
      "riz",
      9
    ],
    [
      "aýdyp",
      9
    ],
    [
      "döretmek",
      8
    ],
    [
      "döwrebaplaşdyrmak",
      8
    ],
    [
      "john",
      8
    ],
    [
      "deere",
      8
    ],
    [
      "gerimli",
      7
    ],
    [
      "durmuş-ykdysady",
      7
    ],
    [
      "ýaşaýyş-durmuş",
      7
    ],
    [
      "toplumlaýyn",
      7
    ],
    [
      "yglan",
      7
    ],
    [
      "bermek",
      7
    ],
    [
      "biridir",
      7
    ],
    [
      "özünde",
      7
    ],
    [
      "öndürmek",
      7
    ],
    [
      "taýýarlamak",
      7
    ],
    [
      "ugry",
      7
    ],
    [
      "geçirmek",
      7
    ],
    [
      "bmg-niň",
      7
    ],
    [
      "döwletiniň",
      7
    ],
    [
      "abş",
      7
    ],
    [
      "işewürlik",
      7
    ],
    [
      "kabinetiniň",
      6
    ],
    [
      "bellenildi",
      6
    ],
    [
      "gowulandyrmak",
      6
    ],
    [
      "giňeltmek",
      6
    ],
    [
      "bolşy",
      6
    ],
    [
      "bellemek",
      6
    ],
    [
      "pugtalandyrmaga",
      6
    ],
    [
      "bellenilen",
      6
    ],
    [
      "oňyn",
      6
    ],
    [
      "hususan-da",
      6
    ],
    [
      "gatnaşmagynda",
      6
    ],
    [
      "hyzmatdaşlyga",
      6
    ],
    [
      "geňeşiniň",
      6
    ],
    [
      "al-arabiýa",
      6
    ],
    [
      "teleýaýlymynyň",
      6
    ],
    [
      "rizwan",
      6
    ],
    [
      "florida",
      6
    ],
    [
      "ynanyşmak",
      6
    ],
    [
      "düzümleriniň",
      6
    ],
    [
      "mejlisinde",
      5
    ],
    [
      "galkynyşy",
      5
    ],
    [
      "eden",
      5
    ],
    [
      "paýtagtymyzda",
      5
    ],
    [
      "pugtalandyrmak",
      5
    ],
    [
      "goýlan",
      5
    ],
    [
      "kämilleşdirmek",
      5
    ],
    [
      "ornaşdyrmak",
      5
    ],
    [
      "saklamak",
      5
    ],
    [
      "köpugurly",
      5
    ],
    [
      "döredildi",
      5
    ],
    [
      "döwletleriniň",
      5
    ],
    [
      "önümleriniň",
      5
    ],
    [
      "giňeltmäge",
      5
    ],
    [
      "gurmak",
      5
    ],
    [
      "edilmegi",
      5
    ],
    [
      "ýazylmak",
      5
    ],
    [
      "halkbank",
      5
    ],
    [
      "and",
      5
    ],
    [
      "other",
      5
    ],
    [
      "services",
      5
    ],
    [
      "ýöriteleşdirilen",
      5
    ],
    [
      "serişdeleriniň",
      5
    ],
    [
      "bedewleriniň",
      5
    ]
  ]
}