{
  "test_date": "2026-03-07T15:01:30.367448",
  "corpus_file": "metbugat_corpus.txt",
  "total_corpus_words": 697285,
  "sample_size": 20000,
  "results": {
    "total_tokens": 20000,
    "total_types": 5504,
    "recognized_tokens": 15111,
    "unrecognized_tokens": 4889,
    "recognized_types": 3552,
    "unrecognized_types": 1952,
    "token_coverage_pct": 75.56,
    "type_coverage_pct": 64.53,
    "pos_distribution": {
      "noun": 3037,
      "verb": 515
    }
  },
  "error_categories": {
    "diger": {
      "type_count": 1293,
      "token_count": 3032,
      "top_examples": [
        [
          "la",
          58
        ],
        [
          "le",
          54
        ],
        [
          "ry",
          37
        ],
        [
          "nyň",
          36
        ],
        [
          "ri",
          33
        ],
        [
          "li",
          32
        ],
        [
          "adyndaky",
          32
        ],
        [
          "ra",
          30
        ],
        [
          "arasyndaky",
          30
        ],
        [
          "ly",
          30
        ],
        [
          "mundan",
          30
        ],
        [
          "dy",
          29
        ],
        [
          "ösüş",
          27
        ],
        [
          "de",
          26
        ],
        [
          "ta",
          24
        ],
        [
          "bi",
          23
        ],
        [
          "na",
          22
        ],
        [
          "ny",
          22
        ],
        [
          "ma",
          21
        ],
        [
          "munuň",
          20
        ]
      ]
    },
    "fiilimsi_zarf": {
      "type_count": 183,
      "token_count": 523,
      "top_examples": [
        [
          "alnyp",
          46
        ],
        [
          "ynanyşmak",
          29
        ],
        [
          "geçirmek",
          17
        ],
        [
          "etmäge",
          14
        ],
        [
          "geçirilmegi",
          12
        ],
        [
          "goramak",
          12
        ],
        [
          "döretmek",
          11
        ],
        [
          "ýazylmak",
          11
        ],
        [
          "diýlip",
          11
        ],
        [
          "hormatlamak",
          10
        ],
        [
          "bellemek",
          9
        ],
        [
          "bermek",
          8
        ],
        [
          "ulanmaga",
          8
        ],
        [
          "goýmak",
          8
        ],
        [
          "edip",
          8
        ],
        [
          "hormatlanylýan",
          6
        ],
        [
          "aýdyp",
          6
        ],
        [
          "döretmäge",
          6
        ],
        [
          "düşünişmek",
          5
        ],
        [
          "ynanyşmagy",
          5
        ]
      ]
    },
    "tireli_bilesik": {
      "type_count": 158,
      "token_count": 498,
      "top_examples": [
        [
          "hem-de",
          118
        ],
        [
          "beýläk-de",
          38
        ],
        [
          "has-da",
          29
        ],
        [
          "bmg-niň",
          26
        ],
        [
          "hususan-da",
          14
        ],
        [
          "haýyr-sahawat",
          10
        ],
        [
          "ýene-de",
          9
        ],
        [
          "başga-da",
          8
        ],
        [
          "durmuş-ykdysady",
          8
        ],
        [
          "şeýle-de",
          8
        ],
        [
          "medeni-ynsanperwer",
          8
        ],
        [
          "syýasy-diplomatik",
          6
        ],
        [
          "ýaşaýyş-durmuş",
          6
        ],
        [
          "söwda-ykdysady",
          6
        ],
        [
          "wise-prezidenti",
          5
        ],
        [
          "görä-de",
          5
        ],
        [
          "birek-birege",
          5
        ],
        [
          "geljekde-de",
          4
        ],
        [
          "gönüden-göni",
          4
        ],
        [
          "taryhy-medeni",
          4
        ]
      ]
    },
    "ettirgen_edilgen": {
      "type_count": 143,
      "token_count": 325,
      "top_examples": [
        [
          "ösdürmek",
          22
        ],
        [
          "gönükdirilen",
          18
        ],
        [
          "pugtalandyrmaga",
          15
        ],
        [
          "ösdürmegiň",
          15
        ],
        [
          "ösdürmäge",
          11
        ],
        [
          "gönükdirilendir",
          10
        ],
        [
          "kämilleşdirmek",
          10
        ],
        [
          "ýokarlandyrmaga",
          8
        ],
        [
          "ornaşdyrmak",
          6
        ],
        [
          "döredilen",
          6
        ],
        [
          "ýokarlandyrmak",
          6
        ],
        [
          "pugtalandyrmak",
          5
        ],
        [
          "ösdürmekde",
          5
        ],
        [
          "ýöriteleşdirilen",
          5
        ],
        [
          "artdyrmak",
          5
        ],
        [
          "ruhlandyrýar",
          5
        ],
        [
          "dolandyrmak",
          4
        ],
        [
          "etdirilýär",
          4
        ],
        [
          "ösdürmegi",
          4
        ],
        [
          "meýilleşdirilýän",
          4
        ]
      ]
    },
    "yapim_ekli": {
      "type_count": 53,
      "token_count": 134,
      "top_examples": [
        [
          "üstünlikli",
          22
        ],
        [
          "gerimli",
          16
        ],
        [
          "arkadagly",
          11
        ],
        [
          "köpugurly",
          7
        ],
        [
          "öňdengörüjilikli",
          6
        ],
        [
          "işewürlik",
          6
        ],
        [
          "ynsanperwerlik",
          5
        ],
        [
          "söýüjilikli",
          4
        ],
        [
          "hilli",
          4
        ],
        [
          "ýurtly",
          4
        ],
        [
          "fransuz",
          3
        ],
        [
          "buýsançly",
          2
        ],
        [
          "ygrarly",
          2
        ],
        [
          "ugurly",
          2
        ],
        [
          "oýlanyşykly",
          2
        ],
        [
          "sinandali",
          1
        ],
        [
          "köpöwüşginli",
          1
        ],
        [
          "darajali",
          1
        ],
        [
          "köpşahaly",
          1
        ],
        [
          "agroinženerçilik",
          1
        ]
      ]
    },
    "fiil_cekimi": {
      "type_count": 58,
      "token_count": 112,
      "top_examples": [
        [
          "köptaraplaýyn",
          11
        ],
        [
          "döredildi",
          8
        ],
        [
          "bellenildi",
          8
        ],
        [
          "ynanýaryn",
          6
        ],
        [
          "sebitleýin",
          6
        ],
        [
          "plenar",
          4
        ],
        [
          "toplumlaýyn",
          4
        ],
        [
          "maksatnamalaýyn",
          4
        ],
        [
          "tassyklanyldy",
          3
        ],
        [
          "seýitnazar",
          3
        ],
        [
          "amangeldi",
          3
        ],
        [
          "girizildi",
          3
        ],
        [
          "meýilnamalaýyn",
          2
        ],
        [
          "kesgitlenildi",
          2
        ],
        [
          "gowşuryldy",
          2
        ],
        [
          "naser",
          1
        ],
        [
          "söýüjiler",
          1
        ],
        [
          "alber",
          1
        ],
        [
          "berger",
          1
        ],
        [
          "gurbangeldy",
          1
        ]
      ]
    },
    "sira_sayi": {
      "type_count": 1,
      "token_count": 99,
      "top_examples": [
        [
          "nji",
          99
        ]
      ]
    },
    "ozel_isim": {
      "type_count": 6,
      "token_count": 72,
      "top_examples": [
        [
          "berdimuhamedow",
          30
        ],
        [
          "berdimuhamedowyň",
          15
        ],
        [
          "berdimuhamedowa",
          12
        ],
        [
          "türkmenistandaky",
          11
        ],
        [
          "türkmenistanly",
          3
        ],
        [
          "türkmenistanlylara",
          1
        ]
      ]
    },
    "cok_ekli_isim": {
      "type_count": 43,
      "token_count": 57,
      "top_examples": [
        [
          "şolaryň",
          6
        ],
        [
          "ösüşleriň",
          3
        ],
        [
          "alyşmalaryň",
          3
        ],
        [
          "taýýarlamalary",
          2
        ],
        [
          "bilermenleri",
          2
        ],
        [
          "şaýollaryň",
          2
        ],
        [
          "geňeşmeleri",
          2
        ],
        [
          "türkmengallaönümleri",
          2
        ],
        [
          "ýetişmekleri",
          1
        ],
        [
          "wekiliýetleriň",
          1
        ],
        [
          "diňleýjileri",
          1
        ],
        [
          "daşamalaryny",
          1
        ],
        [
          "gyzyklanmalary",
          1
        ],
        [
          "netijenamalaryny",
          1
        ],
        [
          "innowasiýalaryň",
          1
        ],
        [
          "kinofestiwallaryň",
          1
        ],
        [
          "işlemekleri",
          1
        ],
        [
          "ösüşlerini",
          1
        ],
        [
          "maslahatlaşmalaryň",
          1
        ],
        [
          "gyzyklanýanlaryň",
          1
        ]
      ]
    },
    "yabanci": {
      "type_count": 14,
      "token_count": 37,
      "top_examples": [
        [
          "innowasion",
          13
        ],
        [
          "other",
          9
        ],
        [
          "golf",
          2
        ],
        [
          "menejment",
          2
        ],
        [
          "parlamentara",
          2
        ],
        [
          "institusional",
          1
        ],
        [
          "holding",
          1
        ],
        [
          "sion",
          1
        ],
        [
          "waşingtonda",
          1
        ],
        [
          "toph",
          1
        ],
        [
          "marketing",
          1
        ],
        [
          "finishing",
          1
        ],
        [
          "brifingler",
          1
        ],
        [
          "brifingini",
          1
        ]
      ]
    }
  },
  "top_unrecognized_100": [
    [
      "hem-de",
      118
    ],
    [
      "nji",
      99
    ],
    [
      "la",
      58
    ],
    [
      "le",
      54
    ],
    [
      "alnyp",
      46
    ],
    [
      "beýläk-de",
      38
    ],
    [
      "ry",
      37
    ],
    [
      "nyň",
      36
    ],
    [
      "ri",
      33
    ],
    [
      "li",
      32
    ],
    [
      "adyndaky",
      32
    ],
    [
      "berdimuhamedow",
      30
    ],
    [
      "ra",
      30
    ],
    [
      "arasyndaky",
      30
    ],
    [
      "ly",
      30
    ],
    [
      "mundan",
      30
    ],
    [
      "ynanyşmak",
      29
    ],
    [
      "dy",
      29
    ],
    [
      "has-da",
      29
    ],
    [
      "ösüş",
      27
    ],
    [
      "de",
      26
    ],
    [
      "bmg-niň",
      26
    ],
    [
      "ta",
      24
    ],
    [
      "bi",
      23
    ],
    [
      "na",
      22
    ],
    [
      "ny",
      22
    ],
    [
      "ösdürmek",
      22
    ],
    [
      "üstünlikli",
      22
    ],
    [
      "ma",
      21
    ],
    [
      "munuň",
      20
    ],
    [
      "halkbank",
      20
    ],
    [
      "gy",
      18
    ],
    [
      "gönükdirilen",
      18
    ],
    [
      "yglan",
      18
    ],
    [
      "bilelikdäki",
      18
    ],
    [
      "ka",
      17
    ],
    [
      "nis",
      17
    ],
    [
      "geçirmek",
      17
    ],
    [
      "niň",
      17
    ],
    [
      "and",
      17
    ],
    [
      "gülläp",
      17
    ],
    [
      "gerimli",
      16
    ],
    [
      "ti",
      15
    ],
    [
      "berdimuhamedowyň",
      15
    ],
    [
      "den",
      15
    ],
    [
      "pugtalandyrmaga",
      15
    ],
    [
      "ösdürmegiň",
      15
    ],
    [
      "hususan-da",
      14
    ],
    [
      "mi",
      14
    ],
    [
      "mak",
      14
    ],
    [
      "services",
      14
    ],
    [
      "etmäge",
      14
    ],
    [
      "edýän",
      14
    ],
    [
      "my",
      14
    ],
    [
      "sy",
      14
    ],
    [
      "ler",
      13
    ],
    [
      "galkynyşy",
      13
    ],
    [
      "innowasion",
      13
    ],
    [
      "di",
      13
    ],
    [
      "döwletara",
      13
    ],
    [
      "şunda",
      13
    ],
    [
      "geçirilmegi",
      12
    ],
    [
      "berdimuhamedowa",
      12
    ],
    [
      "ty",
      12
    ],
    [
      "ni",
      12
    ],
    [
      "goramak",
      12
    ],
    [
      "ki",
      11
    ],
    [
      "ösdürmäge",
      11
    ],
    [
      "döretmek",
      11
    ],
    [
      "du",
      11
    ],
    [
      "köptaraplaýyn",
      11
    ],
    [
      "lan",
      11
    ],
    [
      "arkadagly",
      11
    ],
    [
      "oňyn",
      11
    ],
    [
      "ýazylmak",
      11
    ],
    [
      "lik",
      11
    ],
    [
      "türkmenistandaky",
      11
    ],
    [
      "se",
      11
    ],
    [
      "kabinetiniň",
      11
    ],
    [
      "len",
      11
    ],
    [
      "diýlip",
      11
    ],
    [
      "respublikasyndaky",
      10
    ],
    [
      "gi",
      10
    ],
    [
      "haýyr-sahawat",
      10
    ],
    [
      "birnäçe",
      10
    ],
    [
      "gönükdirilendir",
      10
    ],
    [
      "kämilleşdirmek",
      10
    ],
    [
      "ryň",
      10
    ],
    [
      "hormatlamak",
      10
    ],
    [
      "si",
      10
    ],
    [
      "çi",
      10
    ],
    [
      "riň",
      10
    ],
    [
      "ýene-de",
      9
    ],
    [
      "bellemek",
      9
    ],
    [
      "ha",
      9
    ],
    [
      "dyr",
      9
    ],
    [
      "other",
      9
    ],
    [
      "bermek",
      8
    ],
    [
      "bo",
      8
    ],
    [
      "mek",
      8
    ]
  ]
}